babylonian_image_library/__init__.py
babylonian_image_library/babylonian_image_library.py
babylonian_image_library-0.1.4.dist-info/licenses/LICENSE
babylonian_image_library-0.1.4.dist-info/METADATA
babylonian_image_library-0.1.4.dist-info/WHEEL
babylonian_image_library-0.1.4.dist-info/top_level.txt
babylonian_image_library-0.1.4.dist-info/RECORD
