Metadata-Version: 2.4
Name: babylonian-image-library
Version: 0.1.4
Summary: A Python library that generates unique images based on a given seed or address. It also provides functionality to generate random addresses, which can be used to create random images.
Author-email: "A.A. Suvorov" <smartlegiondev@gmail.com>
License-Expression: BSD-3-Clause
Project-URL: Homepage, https://github.com/smartlegionlab/babylonian-image-library
Classifier: Programming Language :: Python :: 3
Classifier: Operating System :: OS Independent
Requires-Python: >=3.6
License-File: LICENSE
Requires-Dist: pillow==11.1.0
Dynamic: license-file
